sentinelseed_promptfoo/__init__.py
sentinelseed_promptfoo/provider.py
sentinelseed_promptfoo-1.0.0.dist-info/METADATA
sentinelseed_promptfoo-1.0.0.dist-info/WHEEL
sentinelseed_promptfoo-1.0.0.dist-info/RECORD
