Metadata-Version: 2.4
Name: sentinelseed-promptfoo
Version: 1.0.0
Summary: Sentinel safety provider for Promptfoo - THSP protocol validation for red-teaming
Project-URL: Homepage, https://sentinelseed.dev
Project-URL: Documentation, https://sentinelseed.dev/docs/promptfoo
Project-URL: Repository, https://github.com/sentinel-seed/sentinel
Project-URL: Issues, https://github.com/sentinel-seed/sentinel/issues
Author-email: Sentinel Team <team@sentinelseed.dev>
License-Expression: MIT
Keywords: ai-safety,alignment,evaluation,llm-testing,promptfoo,red-teaming,sentinel,thsp
Classifier: Development Status :: 4 - Beta
Classifier: Intended Audience :: Developers
Classifier: License :: OSI Approved :: MIT License
Classifier: Programming Language :: Python :: 3
Classifier: Programming Language :: Python :: 3.10
Classifier: Programming Language :: Python :: 3.11
Classifier: Programming Language :: Python :: 3.12
Classifier: Topic :: Scientific/Engineering :: Artificial Intelligence
Classifier: Topic :: Security
Requires-Python: >=3.10
Provides-Extra: all
Requires-Dist: anthropic>=0.20.0; extra == 'all'
Requires-Dist: openai>=1.0.0; extra == 'all'
Provides-Extra: anthropic
Requires-Dist: anthropic>=0.20.0; extra == 'anthropic'
Provides-Extra: openai
Requires-Dist: openai>=1.0.0; extra == 'openai'
